scopt/__init__.py
scopt/__version__.py
scopt/optimizer.py
scopt/instances/__init__.py
scopt/instances/aws.py
scopt/instances/base.py
scopt-0.0.5.dist-info/LICENSE
scopt-0.0.5.dist-info/METADATA
scopt-0.0.5.dist-info/WHEEL
scopt-0.0.5.dist-info/top_level.txt
scopt-0.0.5.dist-info/RECORD
