Metadata-Version: 2.1
Name: scopt
Version: 0.0.5
Summary: Calculate optimized properties of Spark configuration
Home-page: https://github.com/KanchiShimono/scopt
Author: Kanchi Shimono
Author-email: dev.kanchi.shimono@gmail.com
License: MIT
Platform: UNKNOWN
Classifier: Development Status :: 3 - Alpha
Classifier: License :: OSI Approved :: MIT License
Classifier: Operating System :: OS Independent
Classifier: Programming Language :: Python
Classifier: Programming Language :: Python :: 3.8
Classifier: Programming Language :: Python :: 3.9
Classifier: Topic :: Scientific/Engineering
Classifier: Topic :: Utilities
Requires-Python: >=3.8.0
License-File: LICENSE
Provides-Extra: build
Requires-Dist: wheel ; extra == 'build'
Requires-Dist: twine ; extra == 'build'
Requires-Dist: beautifulsoup4 ; extra == 'build'
Provides-Extra: test
Requires-Dist: mypy ; extra == 'test'
Requires-Dist: flake8 ; extra == 'test'
Requires-Dist: black ; extra == 'test'
Requires-Dist: isort ; extra == 'test'
Requires-Dist: pytest ; extra == 'test'
